[
  {
    "file1_path": "/tmp/labeling_duo_coord_uploads/bQYhkwltdKchjivcianTb3_jc_GSXVfe/149242501090e16a/folder1/door2/frame_000141.jpg",
    "file2_path": "/tmp/labeling_duo_coord_uploads/bQYhkwltdKchjivcianTb3_jc_GSXVfe/149242501090e16a/folder2/bottom/frame_000141.jpg",
    "image1_coordinates": [
      {
        "number": 1,
        "x": 2450.856870609711,
        "y": 431.3850391667384
      },
      {
        "number": 2,
        "x": 2468.766037662375,
        "y": 744.7954625883523
      },
      {
        "number": 3,
        "x": 2397.1293694517203,
        "y": 1147.7517212732846
      },
      {
        "number": 4,
        "x": 2240.4241577409134,
        "y": 435.8623309299043
      },
      {
        "number": 5,
        "x": 1944.922901371963,
        "y": 243.33878511377006
      },
      {
        "number": 6,
        "x": 1953.8774848982948,
        "y": 426.9077474035725
      },
      {
        "number": 7,
        "x": 1725.5356049768334,
        "y": 158.2702416136177
      },
      {
        "number": 8,
        "x": 1980.7412354772905,
        "y": 776.1365049305138
      },
      {
        "number": 9,
        "x": 1958.3547766614608,
        "y": 1008.9556766151412
      },
      {
        "number": 10,
        "x": 1631.5124779503492,
        "y": 180.65670042944726
      },
      {
        "number": 11,
        "x": 1618.0806026608514,
        "y": 1246.2521400629346
      },
      {
        "number": 12,
        "x": 1161.3968428179282,
        "y": 1268.6385988787642
      },
      {
        "number": 13,
        "x": 1139.0103840020988,
        "y": 247.81607687693597
      },
      {
        "number": 14,
        "x": 1130.055800475767,
        "y": 413.4758721140748
      },
      {
        "number": 15,
        "x": 1134.5330922389328,
        "y": 556.749208535384
      },
      {
        "number": 16,
        "x": 1121.1012169494352,
        "y": 691.0679614303614
      },
      {
        "number": 17,
        "x": 1121.1012169494352,
        "y": 820.9094225621728
      },
      {
        "number": 18,
        "x": 1147.9649675284306,
        "y": 986.5692177993117
      },
      {
        "number": 19,
        "x": 1156.9195510547625,
        "y": 1116.4106789311231
      },
      {
        "number": 20,
        "x": 1183.783301633758,
        "y": 1255.2067235892664
      },
      {
        "number": 21,
        "x": 883.8047535016417,
        "y": 306.02086979809286
      },
      {
        "number": 22,
        "x": 856.9410029226462,
        "y": 435.8623309299043
      },
      {
        "number": 23,
        "x": 830.0772523436507,
        "y": 717.9317120093568
      },
      {
        "number": 24,
        "x": 874.8501699753099,
        "y": 847.7731731411683
      },
      {
        "number": 25,
        "x": 624.1218312380187,
        "y": 914.932549588657
      },
      {
        "number": 26,
        "x": 624.1218312380187,
        "y": 1000.0010930888094
      },
      {
        "number": 27,
        "x": 677.8493323960097,
        "y": 597.0448344038772
      },
      {
        "number": 28,
        "x": 668.8947488696779,
        "y": 485.11254032472937
      }
    ],
    "image2_coordinates": [
      {
        "number": 1,
        "x": 1125.8499171060437,
        "y": 86.6478818104853
      },
      {
        "number": 2,
        "x": 1524.3218741497756,
        "y": 73.21624280901119
      },
      {
        "number": 3,
        "x": 1976.5203871994038,
        "y": 77.69345580950257
      },
      {
        "number": 4,
        "x": 1193.0081121134142,
        "y": 203.0554198232609
      },
      {
        "number": 5,
        "x": 951.2386100868803,
        "y": 283.64525383210554
      },
      {
        "number": 6,
        "x": 1175.0992601114488,
        "y": 274.6908278311228
      },
      {
        "number": 7,
        "x": 866.1715630775442,
        "y": 243.3503368276832
      },
      {
        "number": 8,
        "x": 1555.662365153215,
        "y": 265.73640183014004
      },
      {
        "number": 9,
        "x": 1810.863506181223,
        "y": 270.21361483063146
      },
      {
        "number": 10,
        "x": 843.7854980750874,
        "y": 337.371809838002
      },
      {
        "number": 11,
        "x": 2285.4480842333082,
        "y": 346.3262358389847
      },
      {
        "number": 12,
        "x": 2477.968243254437,
        "y": 503.0286908561826
      },
      {
        "number": 13,
        "x": 790.058942069191,
        "y": 476.1654128532344
      },
      {
        "number": 14,
        "x": 996.0107400917939,
        "y": 449.30213485028617
      },
      {
        "number": 15,
        "x": 1219.8713901163624,
        "y": 449.30213485028617
      },
      {
        "number": 16,
        "x": 1416.8687621379827,
        "y": 444.8249218497948
      },
      {
        "number": 17,
        "x": 1681.0243291669733,
        "y": 444.8249218497948
      },
      {
        "number": 18,
        "x": 1927.2710441939987,
        "y": 458.25656085126894
      },
      {
        "number": 19,
        "x": 2160.0861202195497,
        "y": 458.25656085126894
      },
      {
        "number": 20,
        "x": 2316.788575236748,
        "y": 458.25656085126894
      },
      {
        "number": 21,
        "x": 548.289440042657,
        "y": 767.1842578851733
      },
      {
        "number": 22,
        "x": 799.0133680701737,
        "y": 753.7526188836993
      },
      {
        "number": 23,
        "x": 1434.7776141399481,
        "y": 753.7526188836993
      },
      {
        "number": 24,
        "x": 1689.978755167956,
        "y": 753.7526188836993
      },
      {
        "number": 25,
        "x": 1595.9572821576373,
        "y": 1617.8547279785334
      },
      {
        "number": 26,
        "x": 2088.450712211688,
        "y": 1608.9003019775507
      },
      {
        "number": 27,
        "x": 897.5120540809838,
        "y": 1138.792936925957
      },
      {
        "number": 28,
        "x": 476.65403203479514,
        "y": 1174.610640929888
      }
    ]
  },
  {
    "file1_path": "/tmp/labeling_duo_coord_uploads/bQYhkwltdKchjivcianTb3_jc_GSXVfe/149242501090e16a/folder1/door2/frame_000226.jpg",
    "file2_path": "/tmp/labeling_duo_coord_uploads/bQYhkwltdKchjivcianTb3_jc_GSXVfe/149242501090e16a/folder2/bottom/frame_000225.jpg",
    "image1_coordinates": [
      {
        "number": 1,
        "x": 2249.378741267245,
        "y": 579.1356673512136
      },
      {
        "number": 2,
        "x": 2347.879160056895,
        "y": 1201.4792224312755
      },
      {
        "number": 3,
        "x": 2146.401030714429,
        "y": 556.749208535384
      },
      {
        "number": 4,
        "x": 1609.1260191345195,
        "y": 489.5898320878953
      },
      {
        "number": 5,
        "x": 1761.3539390821607,
        "y": 489.5898320878953
      },
      {
        "number": 6,
        "x": 1806.1268567138197,
        "y": 668.6815026145318
      },
      {
        "number": 7,
        "x": 1850.8997743454788,
        "y": 919.4098413518229
      },
      {
        "number": 8,
        "x": 1573.3076850291923,
        "y": 538.8400414827203
      },
      {
        "number": 9,
        "x": 1219.6016357390852,
        "y": 538.8400414827203
      },
      {
        "number": 10,
        "x": 937.5322546596326,
        "y": 556.749208535384
      },
      {
        "number": 11,
        "x": 1438.988932134215,
        "y": 888.0687990096616
      },
      {
        "number": 12,
        "x": 1501.6710168185377,
        "y": 986.5692177993117
      },
      {
        "number": 13,
        "x": 1443.4662238973808,
        "y": 1089.5469283521277
      },
      {
        "number": 14,
        "x": 950.9641299491303,
        "y": 614.9540014565408
      },
      {
        "number": 15,
        "x": 946.4868381859644,
        "y": 691.0679614303614
      },
      {
        "number": 16,
        "x": 933.0549628964667,
        "y": 776.1365049305138
      },
      {
        "number": 17,
        "x": 915.1457958438031,
        "y": 870.1596319569979
      },
      {
        "number": 18,
        "x": 888.2820452648076,
        "y": 968.6600507466479
      },
      {
        "number": 19,
        "x": 883.8047535016417,
        "y": 1076.1150530626298
      },
      {
        "number": 20,
        "x": 874.8501699753099,
        "y": 1170.138180089114
      },
      {
        "number": 21,
        "x": 870.372878212144,
        "y": 1291.0250576945937
      },
      {
        "number": 22,
        "x": 883.8047535016417,
        "y": 605.999417930209
      },
      {
        "number": 23,
        "x": 865.8955864489781,
        "y": 776.1365049305138
      },
      {
        "number": 24,
        "x": 825.5999605804848,
        "y": 879.1142154833298
      }
    ],
    "image2_coordinates": [
      {
        "number": 1,
        "x": 1134.8043431070264,
        "y": 91.12509481097668
      },
      {
        "number": 2,
        "x": 1980.997600199895,
        "y": 73.21624280901119
      },
      {
        "number": 3,
        "x": 1081.0777871011298,
        "y": 117.98837281392488
      },
      {
        "number": 4,
        "x": 866.1715630775442,
        "y": 247.8275498281746
      },
      {
        "number": 5,
        "x": 933.3297580849147,
        "y": 198.57820682276952
      },
      {
        "number": 6,
        "x": 1179.57647311194,
        "y": 256.7819758291573
      },
      {
        "number": 7,
        "x": 1560.1395781537065,
        "y": 270.21361483063146
      },
      {
        "number": 8,
        "x": 857.2171370765615,
        "y": 319.4629578360365
      },
      {
        "number": 9,
        "x": 633.3564870519931,
        "y": 534.3691818596222
      },
      {
        "number": 10,
        "x": 261.74780801120943,
        "y": 874.6373698969662
      },
      {
        "number": 11,
        "x": 1466.1181051433878,
        "y": 382.14393984291564
      },
      {
        "number": 12,
        "x": 1658.6382641645166,
        "y": 382.14393984291564
      },
      {
        "number": 13,
        "x": 1860.1128491866282,
        "y": 377.6667268424243
      },
      {
        "number": 14,
        "x": 503.51731003774336,
        "y": 843.2968788935267
      },
      {
        "number": 15,
        "x": 754.2412380652601,
        "y": 838.8196658930353
      },
      {
        "number": 16,
        "x": 1072.1233611001471,
        "y": 838.8196658930353
      },
      {
        "number": 17,
        "x": 1354.1877801311034,
        "y": 834.3424528925439
      },
      {
        "number": 18,
        "x": 1734.7508851728699,
        "y": 838.8196658930353
      },
      {
        "number": 19,
        "x": 2146.654481218076,
        "y": 838.8196658930353
      },
      {
        "number": 20,
        "x": 2366.037918242153,
        "y": 838.8196658930353
      },
      {
        "number": 21,
        "x": 2630.193485271144,
        "y": 856.7285178950008
      },
      {
        "number": 22,
        "x": 346.81485502054545,
        "y": 1017.90818591269
      },
      {
        "number": 23,
        "x": 964.6702490883544,
        "y": 1102.975232922026
      },
      {
        "number": 24,
        "x": 1322.8472891276638,
        "y": 1085.0663809200605
      }
    ]
  },
  {
    "file1_path": "/tmp/labeling_duo_coord_uploads/bQYhkwltdKchjivcianTb3_jc_GSXVfe/149242501090e16a/folder1/door2/frame_000252.jpg",
    "file2_path": "/tmp/labeling_duo_coord_uploads/bQYhkwltdKchjivcianTb3_jc_GSXVfe/149242501090e16a/folder2/bottom/frame_000252.jpg",
    "image1_coordinates": [
      {
        "number": 1,
        "x": 2531.448122346698,
        "y": 426.9077474035725
      },
      {
        "number": 2,
        "x": 2531.448122346698,
        "y": 803.0002555095092
      },
      {
        "number": 3,
        "x": 2410.561244741218,
        "y": 1179.0927636154458
      },
      {
        "number": 4,
        "x": 2052.377903687945,
        "y": 279.15711921909735
      },
      {
        "number": 5,
        "x": 2038.9460283984472,
        "y": 749.2727543515182
      },
      {
        "number": 6,
        "x": 2003.12769429312,
        "y": 1000.0010930888094
      },
      {
        "number": 7,
        "x": 2034.4687366352814,
        "y": 1219.3883894839391
      },
      {
        "number": 8,
        "x": 1640.467061476681,
        "y": 1255.2067235892664
      },
      {
        "number": 9,
        "x": 1125.578508712601,
        "y": 1237.2975565366028
      },
      {
        "number": 10,
        "x": 771.8724594224939,
        "y": 1201.4792224312755
      },
      {
        "number": 11,
        "x": 458.46203600087995,
        "y": 422.4304556404066
      },
      {
        "number": 12,
        "x": 453.98474423771404,
        "y": 503.021707377393
      },
      {
        "number": 13,
        "x": 449.50745247454813,
        "y": 614.9540014565408
      },
      {
        "number": 14,
        "x": 458.46203600087995,
        "y": 726.8862955356886
      },
      {
        "number": 15,
        "x": 485.3257865798754,
        "y": 843.2958813780024
      },
      {
        "number": 16,
        "x": 512.1895371588708,
        "y": 964.182758983482
      },
      {
        "number": 17,
        "x": 543.5305795010323,
        "y": 1071.637761299464
      },
      {
        "number": 18,
        "x": 588.3034971326914,
        "y": 1156.7063047996164
      },
      {
        "number": 19,
        "x": 1022.600798159785,
        "y": 185.1339921926132
      },
      {
        "number": 20,
        "x": 1022.600798159785,
        "y": 332.8846203770883
      },
      {
        "number": 21,
        "x": 677.8493323960097,
        "y": 708.977128483025
      },
      {
        "number": 22,
        "x": 677.8493323960097,
        "y": 843.2958813780024
      },
      {
        "number": 23,
        "x": 1434.511640371049,
        "y": 641.8177520355363
      },
      {
        "number": 24,
        "x": 1519.5801838712014,
        "y": 816.4321307990069
      },
      {
        "number": 25,
        "x": 1438.988932134215,
        "y": 977.6146342729799
      },
      {
        "number": 26,
        "x": 1434.511640371049,
        "y": 1134.3198459837868
      }
    ],
    "image2_coordinates": [
      {
        "number": 1,
        "x": 1134.8043431070264,
        "y": 86.6478818104853
      },
      {
        "number": 2,
        "x": 1542.230726151741,
        "y": 55.30739080704572
      },
      {
        "number": 3,
        "x": 1994.4292392013692,
        "y": 86.6478818104853
      },
      {
        "number": 4,
        "x": 1081.0777871011298,
        "y": 265.73640183014004
      },
      {
        "number": 5,
        "x": 1560.1395781537065,
        "y": 270.21361483063146
      },
      {
        "number": 6,
        "x": 1806.3862931807316,
        "y": 274.6908278311228
      },
      {
        "number": 7,
        "x": 2057.1102212082483,
        "y": 229.9186978262091
      },
      {
        "number": 8,
        "x": 2276.4936582323253,
        "y": 341.84902283849334
      },
      {
        "number": 9,
        "x": 2513.785947258368,
        "y": 507.50590385667397
      },
      {
        "number": 10,
        "x": 2840.622496294238,
        "y": 888.0690088984403
      },
      {
        "number": 11,
        "x": 28.932731985658243,
        "y": 1604.4230889770595
      },
      {
        "number": 12,
        "x": 225.9301040072785,
        "y": 1707.398987988361
      },
      {
        "number": 13,
        "x": 642.3109130529758,
        "y": 1774.5571829957314
      },
      {
        "number": 14,
        "x": 1184.0536861124315,
        "y": 1792.4660349976969
      },
      {
        "number": 15,
        "x": 1806.3862931807316,
        "y": 1792.4660349976969
      },
      {
        "number": 16,
        "x": 2455.58217825198,
        "y": 1787.9888219972056
      },
      {
        "number": 17,
        "x": 2903.303478301117,
        "y": 1711.8762009888521
      },
      {
        "number": 18,
        "x": 3154.027406328634,
        "y": 1608.9003019775507
      },
      {
        "number": 19,
        "x": 727.3779600623118,
        "y": 597.0501638665014
      },
      {
        "number": 20,
        "x": 955.7158230873716,
        "y": 597.0501638665014
      },
      {
        "number": 21,
        "x": 1416.8687621379827,
        "y": 847.774091894018
      },
      {
        "number": 22,
        "x": 1725.7964591718871,
        "y": 847.774091894018
      },
      {
        "number": 23,
        "x": 1457.163679142405,
        "y": 386.621152843407
      },
      {
        "number": 24,
        "x": 1663.1154771650079,
        "y": 391.09836584389836
      },
      {
        "number": 25,
        "x": 1886.9761271895763,
        "y": 382.14393984291564
      },
      {
        "number": 26,
        "x": 2048.155795207266,
        "y": 391.09836584389836
      }
    ]
  }
]